funsies/__init__.py
funsies/_cli.py
funsies/_constants.py
funsies/_context.py
funsies/_dag.py
funsies/_funsies.py
funsies/_getter.py
funsies/_graph.py
funsies/_graphviz.py
funsies/_infer.py
funsies/_logging.py
funsies/_parametrize.py
funsies/_pyfunc.py
funsies/_run.py
funsies/_serdes.py
funsies/_shell.py
funsies/_short_hash.py
funsies/_start_funsies.py
funsies/_storage.py
funsies/_subdag.py
funsies/config.py
funsies/debug.py
funsies/dynamic.py
funsies/errors.py
funsies/fp.py
funsies/parametric.py
funsies/py.typed
funsies/template.py
funsies/types.py
funsies/ui.py
funsies/utils.py
funsies-0.8.1.dist-info/LICENSE
funsies-0.8.1.dist-info/METADATA
funsies-0.8.1.dist-info/WHEEL
funsies-0.8.1.dist-info/entry_points.txt
funsies-0.8.1.dist-info/top_level.txt
funsies-0.8.1.dist-info/RECORD
