Metadata-Version: 2.1
Name: funsies
Version: 0.8.1
Summary: Funsies is a library to build and execution engine for reproducible, composable and data-persistent computational workflows.
Home-page: https://github.com/aspuru-guzik-group/funsies
Author: Cyrille Lavigne
Author-email: cyrille.lavigne@mail.utoronto.ca
License: UNKNOWN
Keywords: workflows hashtree redis compchem chemistry parallel hpc
Platform: UNKNOWN
Classifier: Development Status :: 4 - Beta
Classifier: Typing :: Typed
Classifier: License :: OSI Approved :: MIT License
Classifier: Programming Language :: Python :: 3.7
Classifier: Programming Language :: Python :: 3.8
Classifier: Programming Language :: Python :: 3.9
Classifier: Intended Audience :: Science/Research
Classifier: Topic :: Scientific/Engineering :: Chemistry
Classifier: Topic :: Scientific/Engineering :: Physics
Requires-Python: >=3.7
License-File: LICENSE
Requires-Dist: mypy-extensions
Requires-Dist: redis
Requires-Dist: cloudpickle
Requires-Dist: rq (>=1.7)
Requires-Dist: loguru
Requires-Dist: chevron
Requires-Dist: importlib-metadata (~=1.0) ; python_version < "3.8"
Requires-Dist: typing-extensions ; python_version < "3.8"
